{
  "function": "rosenbrock_4d",
  "label": "iso_long",
  "precondition": false,
  "burn_in": 4,
  "roi_threshold": 8.0,
  "roi_volume": 10.0,
  "sigma": 1.5,
  "grid": 20,
  "global_max": -1.9595299515732214e-12,
  "n_projection_evals": 15361,
  "eval_budget": 15361,
  "n_walkers": 126,
  "steps_per_walker": 120,
  "n_umbrella_evals": 15246,
  "n_in_band": 6440,
  "in_band_fraction": 0.42240587695133147,
  "mean_acceptance": 0.2327823691460055,
  "projection_seconds": 2.5,
  "walker_seconds": 1.3
}